{
	"info": {
		"_postman_id": "1c0ae8df-7921-4fd7-8cf6-7a367e2bdbbb",
		"name": "Exchange",
		"schema": "https://schema.getpostman.com/json/collection/v2.1.0/collection.json"
	},
	"item": [
		{
			"name": "Convert currencies",
			"request": {
				"method": "GET",
				"header": [],
				"url": {
					"raw": "http://localhost:8080/api/v1/exchange?from=USD&to=ARS&value=1",
					"protocol": "http",
					"host": [
						"localhost"
					],
					"port": "8080",
					"path": [
						"api",
						"v1",
						"exchange"
					],
					"query": [
						{
							"key": "from",
							"value": "USD"
						},
						{
							"key": "to",
							"value": "ARS"
						},
						{
							"key": "value",
							"value": "1"
						}
					]
				}
			},
			"response": []
		},
		{
			"name": "List currencies",
			"request": {
				"method": "GET",
				"header": [],
				"url": {
					"raw": "http://localhost:8080/api/v1/exchange/currencies",
					"protocol": "http",
					"host": [
						"localhost"
					],
					"port": "8080",
					"path": [
						"api",
						"v1",
						"exchange",
						"currencies"
					]
				}
			},
			"response": []
		}
	]
}